liteboty/__init__.py
liteboty/cli/__init__.py
liteboty/cli/commands.py
liteboty/cli/templates/project/__init__.py
liteboty/cli/templates/project/config/config.json
liteboty/cli/templates/project/main.py
liteboty/cli/templates/project/services/hello/__init__.py
liteboty/cli/templates/project/services/hello/service.py
liteboty/cli/templates/service/__init__.py
liteboty/cli/templates/service/service.py
liteboty/core/__init__.py
liteboty/core/bot.py
liteboty/core/config.py
liteboty/core/exceptions.py
liteboty/core/message.py
liteboty/core/protos/message.proto
liteboty/core/protos/message_pb2.py
liteboty/core/registry.py
liteboty/core/service.py
liteboty/core/utils.py
liteboty/utils/__init__.py
liteboty/utils/cv_convertors.py
liteboty/utils/datetime_utils.py
liteboty/utils/structure.py
liteboty-0.2.0.dist-info/entry_points.txt
liteboty-0.2.0.dist-info/METADATA
liteboty-0.2.0.dist-info/WHEEL
liteboty-0.2.0.dist-info/RECORD
